best_before/__init__.py
best_before-0.1.0.dist-info/top_level.txt
best_before-0.1.0.dist-info/METADATA
best_before-0.1.0.dist-info/DESCRIPTION.rst
best_before-0.1.0.dist-info/RECORD
best_before-0.1.0.dist-info/metadata.json
best_before-0.1.0.dist-info/WHEEL
